[
  {
    "id": "cljn3x7y00000356z8f4g2h1i",
    "name": "Jane Doe",
    "email": "jane.doe@test.com",
    "email_verified": "2024-01-15T10:30:00.000Z",
    "created_at": "2024-01-15T10:30:00.000Z",
    "updated_at": "2024-01-15T10:30:00.000Z"
  },
  {
    "id": "cljn3x7y00001356z8f4g2h1j",
    "name": "John Doe",
    "email": "johndoe@test.com",
    "email_verified": "2024-01-15T10:31:00.000Z",
    "created_at": "2024-01-15T10:31:00.000Z",
    "updated_at": "2024-01-15T10:31:00.000Z"
  },
  {
    "id": "cljn3x7y00002356z8f4g2h1k",
    "name": "John Hancock",
    "email": "johnhancock@test.com",
    "email_verified": "2024-01-15T10:32:00.000Z",
    "created_at": "2024-01-15T10:32:00.000Z",
    "updated_at": "2024-01-15T10:32:00.000Z"
  },
  {
    "id": "cljn3x7y00003356z8f4g2h1l",
    "name": "Jane Hancock",
    "email": "janehancock@test.com",
    "email_verified": null,
    "created_at": "2024-01-15T10:33:00.000Z",
    "updated_at": "2024-01-15T10:33:00.000Z"
  },
  {
    "id": "cljn3x7y00004356z8f4g2h1m",
    "name": "Alice Smith",
    "email": "alicesmith@test.com",
    "email_verified": "2024-01-16T09:15:00.000Z",
    "created_at": "2024-01-16T09:15:00.000Z",
    "updated_at": "2024-01-16T09:15:00.000Z"
  },
  {
    "id": "cljn3x7y00005356z8f4g2h1n",
    "name": "Bob Johnson",
    "email": "bobjohnson@test.com",
    "email_verified": "2024-01-16T09:20:00.000Z",
    "created_at": "2024-01-16T09:20:00.000Z",
    "updated_at": "2024-01-16T09:20:00.000Z"
  },
  {
    "id": "cljn3x7y00006356z8f4g2h1o",
    "name": "Carol Williams",
    "email": "carolwilliams@test.com",
    "email_verified": "2024-01-16T14:45:00.000Z",
    "created_at": "2024-01-16T14:45:00.000Z",
    "updated_at": "2024-01-16T14:45:00.000Z"
  },
  {
    "id": "cljn3x7y00007356z8f4g2h1p",
    "name": "David Brown",
    "email": "davidbrown@test.com",
    "email_verified": "2024-01-17T08:30:00.000Z",
    "created_at": "2024-01-17T08:30:00.000Z",
    "updated_at": "2024-01-17T08:30:00.000Z"
  },
  {
    "id": "cljn3x7y00008356z8f4g2h1q",
    "name": "Emma Jones",
    "email": "emmajones@test.com",
    "email_verified": "2024-01-17T11:00:00.000Z",
    "created_at": "2024-01-17T11:00:00.000Z",
    "updated_at": "2024-01-17T11:00:00.000Z"
  },
  {
    "id": "cljn3x7y00009356z8f4g2h1r",
    "name": "Frank Garcia",
    "email": "frankgarcia@test.com",
    "email_verified": "2024-01-17T13:30:00.000Z",
    "created_at": "2024-01-17T13:30:00.000Z",
    "updated_at": "2024-01-17T13:30:00.000Z"
  },
  {
    "id": "cljn3x7y00010356z8f4g2h1s",
    "name": "Sarah Connor",
    "email": "sconnor@test.com",
    "email_verified": "2024-01-18T10:00:00.000Z",
    "created_at": "2024-01-18T10:00:00.000Z",
    "updated_at": "2024-01-18T10:00:00.000Z"
  },
  {
    "id": "cljn3x7y00011356z8f4g2h1t",
    "name": "Michael Scott",
    "email": "mscott@test.com",
    "email_verified": "2024-01-18T11:15:00.000Z",
    "created_at": "2024-01-18T11:15:00.000Z",
    "updated_at": "2024-01-18T11:15:00.000Z"
  },
  {
    "id": "cljn3x7y00012356z8f4g2h1u",
    "name": "Leslie Knope",
    "email": "lknope@test.com",
    "email_verified": "2024-01-18T14:30:00.000Z",
    "created_at": "2024-01-18T14:30:00.000Z",
    "updated_at": "2024-01-18T14:30:00.000Z"
  },
  {
    "id": "cljn3x7y00013356z8f4g2h1v",
    "name": "Ron Swanson",
    "email": "rswanson@test.com",
    "email_verified": "2024-01-19T09:00:00.000Z",
    "created_at": "2024-01-19T09:00:00.000Z",
    "updated_at": "2024-01-19T09:00:00.000Z"
  },
  {
    "id": "cljn3x7y00014356z8f4g2h1w",
    "name": "April Ludgate",
    "email": "aludgate@test.com",
    "email_verified": "2024-01-19T10:30:00.000Z",
    "created_at": "2024-01-19T10:30:00.000Z",
    "updated_at": "2024-01-19T10:30:00.000Z"
  },
  {
    "id": "cljn3x7y00015356z8f4g2h1x",
    "name": null,
    "email": "noprofile@test.com",
    "email_verified": "2024-01-20T08:00:00.000Z",
    "created_at": "2024-01-20T08:00:00.000Z",
    "updated_at": "2024-01-20T08:00:00.000Z"
  },
  {
    "id": "cljn3x7y00016356z8f4g2h1y",
    "name": "Grace Hopper",
    "email": "ghopper@test.com",
    "email_verified": null,
    "created_at": "2024-01-20T12:00:00.000Z",
    "updated_at": "2024-01-20T12:00:00.000Z"
  },
  {
    "id": "cljn3x7y00017356z8f4g2h1z",
    "name": "Ada Lovelace",
    "email": "alovelace@test.com",
    "email_verified": "2024-01-20T15:00:00.000Z",
    "created_at": "2024-01-20T15:00:00.000Z",
    "updated_at": "2024-01-20T15:00:00.000Z"
  },
  {
    "id": "cljn3x7y00018356z8f4g2h20",
    "name": "Alan Turing",
    "email": "aturing@test.com",
    "email_verified": "2024-01-21T09:30:00.000Z",
    "created_at": "2024-01-21T09:30:00.000Z",
    "updated_at": "2024-01-21T09:30:00.000Z"
  },
  {
    "id": "cljn3x7y00019356z8f4g2h21",
    "name": "Margaret Hamilton",
    "email": "mhamilton@test.com",
    "email_verified": "2024-01-21T11:00:00.000Z",
    "created_at": "2024-01-21T11:00:00.000Z",
    "updated_at": "2024-01-21T11:00:00.000Z"
  }
]
